barbarians/__init__.py
barbarians/barbarian.py
barbarians/hooks/barbarian_clean_conandata_yml.py
barbarian-0.3.0.dist-info/LICENSE.txt
barbarian-0.3.0.dist-info/METADATA
barbarian-0.3.0.dist-info/WHEEL
barbarian-0.3.0.dist-info/entry_points.txt
barbarian-0.3.0.dist-info/top_level.txt
barbarian-0.3.0.dist-info/RECORD
